{
	"info": {
		"_postman_id": "1b9a9252-d8e6-4493-ac2c-9beea6ba2052",
		"name": "F test cases ",
		"schema": "https://schema.getpostman.com/json/collection/v2.1.0/collection.json"
	},
	"item": [
		{
			"name": "PUT user",
			"request": {
				"method": "PUT",
				"header": [],
				"body": {
					"mode": "raw",
					"raw": ""
				},
				"url": {
					"raw": "{{BASIC_URL}}/users/997d980-ad00-4ee2-a55a-27ff75fbb06X",
					"host": [
						"{{BASIC_URL}}"
					],
					"path": [
						"users",
						"997d980-ad00-4ee2-a55a-27ff75fbb06X"
					]
				}
			},
			"response": []
		},
		{
			"name": "GET user",
			"protocolProfileBehavior": {
				"disableBodyPruning": true
			},
			"request": {
				"method": "GET",
				"header": [],
				"body": {
					"mode": "raw",
					"raw": "",
					"options": {
						"raw": {}
					}
				},
				"url": {
					"raw": "{{Basic_URL}}/user",
					"host": [
						"{{Basic_URL}}"
					],
					"path": [
						"user"
					]
				}
			},
			"response": []
		},
		{
			"name": "PUT user F01",
			"request": {
				"method": "PUT",
				"header": [],
				"url": {
					"raw": "{{BASIC_URL}}/user",
					"host": [
						"{{BASIC_URL}}"
					],
					"path": [
						"user"
					]
				}
			},
			"response": []
		},
		{
			"name": "GET user F02",
			"protocolProfileBehavior": {
				"disableBodyPruning": true
			},
			"request": {
				"method": "GET",
				"header": [],
				"body": {
					"mode": "raw",
					"raw": "",
					"options": {
						"raw": {}
					}
				},
				"url": {
					"raw": "{{Basic_URL}}/user/9997d980-ad00-4ee2-a55a-27ff75fbb061",
					"host": [
						"{{Basic_URL}}"
					],
					"path": [
						"user",
						"9997d980-ad00-4ee2-a55a-27ff75fbb061"
					]
				}
			},
			"response": []
		},
		{
			"name": "PUT user F03",
			"request": {
				"method": "PUT",
				"header": [],
				"body": {
					"mode": "raw",
					"raw": " {\n            \"userId\": \"9997d980-ad00-4ee2-a55a-27ff75fbb061\",\n            \"ssn\": \"197302190599\",\n            \"isPEP\": false,\n            \"isUSCitizen\":0,\n            \"countryOfResidence\": null,\n            \"firstName\": \"Sunne\",\n            \"lastName\": \"Janny Janny Yes pappa\",\n            \"street\": \"Hjortvägen 6\",\n            \"city\": \"Bjurås\",\n            \"postalNumber\": \"17832\",\n            \"salary\": 41000,\n            \"birthYear\": null,\n            \"updatedBy\": null,\n            \"advisory\": null,\n            \"createdAt\": \"2019-04-23T10:30:52.000Z\",\n            \"updatedAt\": \"2020-08-12T11:11:57.000Z\"\n        }"
				},
				"url": {
					"raw": "{{Basic_URL}}/user",
					"host": [
						"{{Basic_URL}}"
					],
					"path": [
						"user"
					]
				}
			},
			"response": []
		},
		{
			"name": "GET user F04",
			"protocolProfileBehavior": {
				"disableBodyPruning": true
			},
			"request": {
				"method": "GET",
				"header": [],
				"body": {
					"mode": "raw",
					"raw": "",
					"options": {
						"raw": {}
					}
				},
				"url": {
					"raw": "{{Basic_URL}}/user/9997d980-ad00-4ee2-a55a-27ff75fbb061",
					"host": [
						"{{Basic_URL}}"
					],
					"path": [
						"user",
						"9997d980-ad00-4ee2-a55a-27ff75fbb061"
					]
				}
			},
			"response": []
		},
		{
			"name": "PUT user F05",
			"request": {
				"method": "PUT",
				"header": [],
				"body": {
					"mode": "raw",
					"raw": "   {\n            \"userId\": \"eu-west-1:29157b90-15cd-4e06-bca9-7b621827cfe0\",\n            \"ssn\": \"195602190501\",\n            \"isPEP\": false,\n            \"isUSCitizen\": false,\n            \"countryOfResidence\": \"SE\",\n            \"firstName\": \"Börje\",\n            \"lastName\": \"Kvarnsveden\",\n            \"street\": \"Gränsgatan 80\",\n            \"city\": null,\n            \"postalNumber\": null,\n            \"salary\": 36000,\n            \"birthYear\": 1956,\n            \"updatedBy\": \"eu-west-1:9997d980-ad00-4ee2-a55a-27ff75fbb06a\",\n            \"advisory\": null,\n            \"createdAt\": \"2019-11-20T10:30:02.000Z\",\n            \"updatedAt\": \"2019-11-20T10:30:02.000Z\"\n        }"
				},
				"url": {
					"raw": "{{Basic_URL}}/user",
					"host": [
						"{{Basic_URL}}"
					],
					"path": [
						"user"
					]
				}
			},
			"response": []
		},
		{
			"name": "GET user F06",
			"protocolProfileBehavior": {
				"disableBodyPruning": true
			},
			"request": {
				"method": "GET",
				"header": [],
				"body": {
					"mode": "raw",
					"raw": "",
					"options": {
						"raw": {}
					}
				},
				"url": {
					"raw": "{{Basic_URL}}/user",
					"host": [
						"{{Basic_URL}}"
					],
					"path": [
						"user"
					]
				}
			},
			"response": []
		},
		{
			"name": "PUT user F07",
			"request": {
				"method": "PUT",
				"header": [],
				"url": {
					"raw": "{{BASIC_URL}}/user",
					"host": [
						"{{BASIC_URL}}"
					],
					"path": [
						"user"
					]
				}
			},
			"response": []
		},
		{
			"name": "GET user F08",
			"protocolProfileBehavior": {
				"disableBodyPruning": true
			},
			"request": {
				"method": "GET",
				"header": [],
				"body": {
					"mode": "raw",
					"raw": "",
					"options": {
						"raw": {}
					}
				},
				"url": {
					"raw": "{{Basic_URL}}/user",
					"host": [
						"{{Basic_URL}}"
					],
					"path": [
						"user"
					]
				}
			},
			"response": []
		},
		{
			"name": "PUT user F09",
			"request": {
				"method": "PUT",
				"header": [],
				"url": {
					"raw": "{{BASIC_URL}}/user",
					"host": [
						"{{BASIC_URL}}"
					],
					"path": [
						"user"
					]
				}
			},
			"response": []
		},
		{
			"name": "GET user F10",
			"protocolProfileBehavior": {
				"disableBodyPruning": true
			},
			"request": {
				"method": "GET",
				"header": [],
				"body": {
					"mode": "raw",
					"raw": "",
					"options": {
						"raw": {}
					}
				},
				"url": {
					"raw": "{{Basic_URL}}/user",
					"host": [
						"{{Basic_URL}}"
					],
					"path": [
						"user"
					]
				}
			},
			"response": []
		},
		{
			"name": "PUT user F11",
			"request": {
				"method": "PUT",
				"header": [],
				"url": {
					"raw": "{{BASIC_URL}}/user",
					"host": [
						"{{BASIC_URL}}"
					],
					"path": [
						"user"
					]
				}
			},
			"response": []
		},
		{
			"name": "GET user F12",
			"protocolProfileBehavior": {
				"disableBodyPruning": true
			},
			"request": {
				"method": "GET",
				"header": [],
				"body": {
					"mode": "raw",
					"raw": "",
					"options": {
						"raw": {}
					}
				},
				"url": {
					"raw": "{{Basic_URL}}/user",
					"host": [
						"{{Basic_URL}}"
					],
					"path": [
						"user"
					]
				}
			},
			"response": []
		},
		{
			"name": "PUT user F13",
			"request": {
				"method": "PUT",
				"header": [],
				"url": {
					"raw": "{{BASIC_URL}}/user",
					"host": [
						"{{BASIC_URL}}"
					],
					"path": [
						"user"
					]
				}
			},
			"response": []
		},
		{
			"name": "GET user F14",
			"protocolProfileBehavior": {
				"disableBodyPruning": true
			},
			"request": {
				"method": "GET",
				"header": [],
				"body": {
					"mode": "raw",
					"raw": "",
					"options": {
						"raw": {}
					}
				},
				"url": {
					"raw": "{{Basic_URL}}/user",
					"host": [
						"{{Basic_URL}}"
					],
					"path": [
						"user"
					]
				}
			},
			"response": []
		},
		{
			"name": "PUT user F15",
			"request": {
				"method": "PUT",
				"header": [],
				"url": {
					"raw": "{{BASIC_URL}}/user",
					"host": [
						"{{BASIC_URL}}"
					],
					"path": [
						"user"
					]
				}
			},
			"response": []
		},
		{
			"name": "GET user F16",
			"protocolProfileBehavior": {
				"disableBodyPruning": true
			},
			"request": {
				"method": "GET",
				"header": [],
				"body": {
					"mode": "raw",
					"raw": "",
					"options": {
						"raw": {}
					}
				},
				"url": {
					"raw": "{{Basic_URL}}/user",
					"host": [
						"{{Basic_URL}}"
					],
					"path": [
						"user"
					]
				}
			},
			"response": []
		},
		{
			"name": "PUT user F17",
			"request": {
				"method": "PUT",
				"header": [],
				"url": {
					"raw": "{{BASIC_URL}}/user",
					"host": [
						"{{BASIC_URL}}"
					],
					"path": [
						"user"
					]
				}
			},
			"response": []
		},
		{
			"name": "GET user F18",
			"protocolProfileBehavior": {
				"disableBodyPruning": true
			},
			"request": {
				"method": "GET",
				"header": [],
				"body": {
					"mode": "raw",
					"raw": "",
					"options": {
						"raw": {}
					}
				},
				"url": {
					"raw": "{{Basic_URL}}/user",
					"host": [
						"{{Basic_URL}}"
					],
					"path": [
						"user"
					]
				}
			},
			"response": []
		},
		{
			"name": "PUT user F19",
			"request": {
				"method": "PUT",
				"header": [],
				"url": {
					"raw": "{{BASIC_URL}}/user",
					"host": [
						"{{BASIC_URL}}"
					],
					"path": [
						"user"
					]
				}
			},
			"response": []
		},
		{
			"name": "GET user F20",
			"protocolProfileBehavior": {
				"disableBodyPruning": true
			},
			"request": {
				"method": "GET",
				"header": [],
				"body": {
					"mode": "raw",
					"raw": "",
					"options": {
						"raw": {}
					}
				},
				"url": {
					"raw": "{{Basic_URL}}/user",
					"host": [
						"{{Basic_URL}}"
					],
					"path": [
						"user"
					]
				}
			},
			"response": []
		},
		{
			"name": "PUT user F21",
			"request": {
				"method": "PUT",
				"header": [],
				"url": {
					"raw": "{{BASIC_URL}}/user",
					"host": [
						"{{BASIC_URL}}"
					],
					"path": [
						"user"
					]
				}
			},
			"response": []
		},
		{
			"name": "GET user F22",
			"protocolProfileBehavior": {
				"disableBodyPruning": true
			},
			"request": {
				"method": "GET",
				"header": [],
				"body": {
					"mode": "raw",
					"raw": "",
					"options": {
						"raw": {}
					}
				},
				"url": {
					"raw": "{{Basic_URL}}/user",
					"host": [
						"{{Basic_URL}}"
					],
					"path": [
						"user"
					]
				}
			},
			"response": []
		},
		{
			"name": "PUT user F23",
			"request": {
				"method": "PUT",
				"header": [],
				"url": {
					"raw": "{{BASIC_URL}}/user",
					"host": [
						"{{BASIC_URL}}"
					],
					"path": [
						"user"
					]
				}
			},
			"response": []
		},
		{
			"name": "GET user F24",
			"protocolProfileBehavior": {
				"disableBodyPruning": true
			},
			"request": {
				"method": "GET",
				"header": [],
				"body": {
					"mode": "raw",
					"raw": "",
					"options": {
						"raw": {}
					}
				},
				"url": {
					"raw": "{{Basic_URL}}/user",
					"host": [
						"{{Basic_URL}}"
					],
					"path": [
						"user"
					]
				}
			},
			"response": []
		},
		{
			"name": "PUT user F25",
			"request": {
				"method": "PUT",
				"header": [],
				"url": {
					"raw": "{{BASIC_URL}}/user",
					"host": [
						"{{BASIC_URL}}"
					],
					"path": [
						"user"
					]
				}
			},
			"response": []
		},
		{
			"name": "GET user F26",
			"protocolProfileBehavior": {
				"disableBodyPruning": true
			},
			"request": {
				"method": "GET",
				"header": [],
				"body": {
					"mode": "raw",
					"raw": "",
					"options": {
						"raw": {}
					}
				},
				"url": {
					"raw": "{{Basic_URL}}/user",
					"host": [
						"{{Basic_URL}}"
					],
					"path": [
						"user"
					]
				}
			},
			"response": []
		},
		{
			"name": "PUT user F27",
			"request": {
				"method": "PUT",
				"header": [],
				"url": {
					"raw": "{{BASIC_URL}}/user",
					"host": [
						"{{BASIC_URL}}"
					],
					"path": [
						"user"
					]
				}
			},
			"response": []
		},
		{
			"name": "GET user F28",
			"protocolProfileBehavior": {
				"disableBodyPruning": true
			},
			"request": {
				"method": "GET",
				"header": [],
				"body": {
					"mode": "raw",
					"raw": "",
					"options": {
						"raw": {}
					}
				},
				"url": {
					"raw": "{{Basic_URL}}/user",
					"host": [
						"{{Basic_URL}}"
					],
					"path": [
						"user"
					]
				}
			},
			"response": []
		},
		{
			"name": "PUT user F29",
			"request": {
				"method": "PUT",
				"header": [],
				"url": {
					"raw": "{{BASIC_URL}}/user",
					"host": [
						"{{BASIC_URL}}"
					],
					"path": [
						"user"
					]
				}
			},
			"response": []
		},
		{
			"name": "GET user F30",
			"protocolProfileBehavior": {
				"disableBodyPruning": true
			},
			"request": {
				"method": "GET",
				"header": [],
				"body": {
					"mode": "raw",
					"raw": "",
					"options": {
						"raw": {}
					}
				},
				"url": {
					"raw": "{{Basic_URL}}/user",
					"host": [
						"{{Basic_URL}}"
					],
					"path": [
						"user"
					]
				}
			},
			"response": []
		},
		{
			"name": "PUT user F31",
			"request": {
				"method": "PUT",
				"header": [],
				"url": {
					"raw": "{{BASIC_URL}}/user",
					"host": [
						"{{BASIC_URL}}"
					],
					"path": [
						"user"
					]
				}
			},
			"response": []
		},
		{
			"name": "GET user F32",
			"protocolProfileBehavior": {
				"disableBodyPruning": true
			},
			"request": {
				"method": "GET",
				"header": [],
				"body": {
					"mode": "raw",
					"raw": "",
					"options": {
						"raw": {}
					}
				},
				"url": {
					"raw": "{{Basic_URL}}/user",
					"host": [
						"{{Basic_URL}}"
					],
					"path": [
						"user"
					]
				}
			},
			"response": []
		},
		{
			"name": "PUT user F33",
			"request": {
				"method": "PUT",
				"header": [],
				"url": {
					"raw": "{{BASIC_URL}}/user",
					"host": [
						"{{BASIC_URL}}"
					],
					"path": [
						"user"
					]
				}
			},
			"response": []
		},
		{
			"name": "GET user F34",
			"protocolProfileBehavior": {
				"disableBodyPruning": true
			},
			"request": {
				"method": "GET",
				"header": [],
				"body": {
					"mode": "raw",
					"raw": "",
					"options": {
						"raw": {}
					}
				},
				"url": {
					"raw": "{{Basic_URL}}/user",
					"host": [
						"{{Basic_URL}}"
					],
					"path": [
						"user"
					]
				}
			},
			"response": []
		},
		{
			"name": "PUT user F35",
			"request": {
				"method": "PUT",
				"header": [],
				"url": {
					"raw": "{{BASIC_URL}}/user",
					"host": [
						"{{BASIC_URL}}"
					],
					"path": [
						"user"
					]
				}
			},
			"response": []
		},
		{
			"name": "GET user F36",
			"protocolProfileBehavior": {
				"disableBodyPruning": true
			},
			"request": {
				"method": "GET",
				"header": [],
				"body": {
					"mode": "raw",
					"raw": "",
					"options": {
						"raw": {}
					}
				},
				"url": {
					"raw": "{{Basic_URL}}/user",
					"host": [
						"{{Basic_URL}}"
					],
					"path": [
						"user"
					]
				}
			},
			"response": []
		},
		{
			"name": "PUT user F37",
			"request": {
				"method": "PUT",
				"header": [],
				"url": {
					"raw": "{{BASIC_URL}}/user",
					"host": [
						"{{BASIC_URL}}"
					],
					"path": [
						"user"
					]
				}
			},
			"response": []
		},
		{
			"name": "GET user F38",
			"protocolProfileBehavior": {
				"disableBodyPruning": true
			},
			"request": {
				"method": "GET",
				"header": [],
				"body": {
					"mode": "raw",
					"raw": "",
					"options": {
						"raw": {}
					}
				},
				"url": {
					"raw": "{{Basic_URL}}/user",
					"host": [
						"{{Basic_URL}}"
					],
					"path": [
						"user"
					]
				}
			},
			"response": []
		},
		{
			"name": "PUT user F39",
			"request": {
				"method": "PUT",
				"header": [],
				"url": {
					"raw": "{{BASIC_URL}}/user",
					"host": [
						"{{BASIC_URL}}"
					],
					"path": [
						"user"
					]
				}
			},
			"response": []
		},
		{
			"name": "GET user F40",
			"protocolProfileBehavior": {
				"disableBodyPruning": true
			},
			"request": {
				"method": "GET",
				"header": [],
				"body": {
					"mode": "raw",
					"raw": "",
					"options": {
						"raw": {}
					}
				},
				"url": {
					"raw": "{{Basic_URL}}/user",
					"host": [
						"{{Basic_URL}}"
					],
					"path": [
						"user"
					]
				}
			},
			"response": []
		},
		{
			"name": "PUT user F41",
			"request": {
				"method": "PUT",
				"header": [],
				"url": {
					"raw": "{{BASIC_URL}}/user",
					"host": [
						"{{BASIC_URL}}"
					],
					"path": [
						"user"
					]
				}
			},
			"response": []
		},
		{
			"name": "GET user F42",
			"protocolProfileBehavior": {
				"disableBodyPruning": true
			},
			"request": {
				"method": "GET",
				"header": [],
				"body": {
					"mode": "raw",
					"raw": "",
					"options": {
						"raw": {}
					}
				},
				"url": {
					"raw": "{{Basic_URL}}/user",
					"host": [
						"{{Basic_URL}}"
					],
					"path": [
						"user"
					]
				}
			},
			"response": []
		},
		{
			"name": "PUT user F43",
			"request": {
				"method": "PUT",
				"header": [],
				"url": {
					"raw": "{{BASIC_URL}}/user",
					"host": [
						"{{BASIC_URL}}"
					],
					"path": [
						"user"
					]
				}
			},
			"response": []
		},
		{
			"name": "GET user F44",
			"protocolProfileBehavior": {
				"disableBodyPruning": true
			},
			"request": {
				"method": "GET",
				"header": [],
				"body": {
					"mode": "raw",
					"raw": "",
					"options": {
						"raw": {}
					}
				},
				"url": {
					"raw": "{{Basic_URL}}/user",
					"host": [
						"{{Basic_URL}}"
					],
					"path": [
						"user"
					]
				}
			},
			"response": []
		},
		{
			"name": "PUT user F45",
			"request": {
				"method": "PUT",
				"header": [],
				"url": {
					"raw": "{{BASIC_URL}}/user",
					"host": [
						"{{BASIC_URL}}"
					],
					"path": [
						"user"
					]
				}
			},
			"response": []
		},
		{
			"name": "GET user F46",
			"protocolProfileBehavior": {
				"disableBodyPruning": true
			},
			"request": {
				"method": "GET",
				"header": [],
				"body": {
					"mode": "raw",
					"raw": "",
					"options": {
						"raw": {}
					}
				},
				"url": {
					"raw": "{{Basic_URL}}/user",
					"host": [
						"{{Basic_URL}}"
					],
					"path": [
						"user"
					]
				}
			},
			"response": []
		},
		{
			"name": "GET users",
			"request": {
				"method": "GET",
				"header": [],
				"url": {
					"raw": "{{Basic_URL}}/usersa",
					"host": [
						"{{Basic_URL}}"
					],
					"path": [
						"usersa"
					]
				}
			},
			"response": []
		},
		{
			"name": "POST user",
			"request": {
				"method": "POST",
				"header": [],
				"url": {
					"raw": "{{Basic_URL}}/user",
					"host": [
						"{{Basic_URL}}"
					],
					"path": [
						"user"
					]
				}
			},
			"response": []
		}
	],
	"protocolProfileBehavior": {}
}